{
  "uuid" : "1df66968984c42bbb66968984cb2bb97",
  "creator" : {
    "firstName" : "Joe",
    "lastName" : "Doe",
    "uuid" : "408e04ceecaf480f8e04ceecafd80f1f"
  },
  "created" : "2018-10-15T13:01:05.920Z",
  "edited" : "2018-10-15T13:01:05.920Z",
  "availableLanguages" : {
    "de" : {
      "published" : true,
      "version" : "1.0",
      "publisher" : {
        "firstName" : "Joe",
        "lastName" : "Doe",
        "uuid" : "f319eada002c42a899eada002cf2a871"
      },
      "publishDate" : "2018-10-15T13:01:05.920Z"
    },
    "en" : {
      "published" : false,
      "version" : "1.1",
      "publisher" : {
        "firstName" : "Joe",
        "lastName" : "Doe",
        "uuid" : "f9ce8716837b47848e8716837b8784ff"
      },
      "publishDate" : "2018-10-15T13:01:05.920Z"
    }
  },
  "languagePaths" : {
    "de" : "/api/v1/yourProject/webroot/Bilder",
    "en" : "/api/v1/yourProject/webroot/Images"
  },
  "parentNode" : {
    "uuid" : "6c7d0272213c4421bd0272213c742150",
    "displayName" : "parentNodeDisplayName"
  },
  "tags" : [ {
    "name" : "red",
    "uuid" : "dde7f1b30c53473ba7f1b30c53d73bb3",
    "tagFamily" : "colors"
  }, {
    "name" : "red",
    "uuid" : "c533fca3df7e4c46b3fca3df7e0c4646",
    "tagFamily" : "colors"
  }, {
    "name" : "green",
    "uuid" : "fa0c2ed9af5f45c38c2ed9af5f75c3ca",
    "tagFamily" : "colors"
  }, {
    "name" : "car",
    "uuid" : "87ca21416d124f998a21416d12ff993e"
  }, {
    "name" : "ship",
    "uuid" : "6ad3d26c03ff466f93d26c03ff066f20"
  } ],
  "childrenInfo" : {
    "folder" : {
      "schemaUuid" : "789290bda0134e109290bda013fe1097",
      "count" : 5
    },
    "blogpost" : {
      "schemaUuid" : "1c8d8c2aee7544278d8c2aee75a42745",
      "count" : 1
    }
  },
  "schema" : {
    "name" : "content",
    "uuid" : "4c3f442c6125425dbf442c6125525d4d",
    "version" : "1.0"
  },
  "container" : false,
  "fields" : {
    "name" : "Name for language tag de-DE",
    "filename" : "dummy-content.de.html",
    "teaser" : "Dummy teaser for de-DE",
    "content" : "Content for language tag de-DE",
    "relatedProduct" : {
      "uuid" : "a24c26917b974e338c26917b97ce3319"
    },
    "price" : 100.1,
    "enabled" : true,
    "branch" : "2018-10-15T13:01:05.920Z",
    "categories" : [ {
      "uuid" : "40613b90dc534bb3a13b90dc53ebb3a4"
    }, {
      "uuid" : "39526597e93146e5926597e93156e50b"
    }, {
      "uuid" : "475e92f326db45189e92f326dbb518a4"
    } ],
    "names" : [ "Jack", "Joe", "Mary", "Tom" ],
    "categoryIds" : [ 1, 42, 133, 7 ],
    "binary" : {
      "fileName" : "flower.jpg",
      "width" : 800,
      "height" : 600,
      "sha512sum" : "ec582eb760034dd91d5fd33656c0b56f082b7365d32e2a139dd9c87ebc192bff3525f32ff4c4137463a31cad020ac19e6e356508db2b90e32d737b6d725e14c1",
      "fileSize" : 95365,
      "mimeType" : "image/jpeg",
      "dominantColor" : "#22a7f0"
    },
    "location" : {
      "uuid" : "ae91b0df1211432491b0df1211432463",
      "microschema" : {
        "name" : "geolocation",
        "uuid" : "0bcfa2207a7e4bb08fa2207a7e8bb046"
      },
      "fields" : {
        "latitude" : 48.208330230278,
        "longitude" : 16.373063840833
      }
    },
    "locations" : [ {
      "uuid" : "628ee00ff3b5422d8ee00ff3b5122d8b",
      "microschema" : {
        "name" : "geolocation",
        "uuid" : "d7104c5fe6fe4a70904c5fe6fe4a7004"
      },
      "fields" : {
        "latitude" : 48.208330230278,
        "longitude" : 16.373063840833
      }
    }, {
      "uuid" : "91b5f4fc28ad494ab5f4fc28ad094a59",
      "microschema" : {
        "name" : "geolocation",
        "uuid" : "9fef2f0b02634ec4af2f0b0263dec437"
      },
      "fields" : {
        "latitude" : 48.137222,
        "longitude" : 11.575556
      }
    } ]
  },
  "path" : "/api/v1/yourProject/webroot/Images",
  "breadcrumb" : [ {
    "uuid" : "7abd6d109b434103bd6d109b430103e7",
    "displayName" : "news",
    "path" : "/news"
  }, {
    "uuid" : "ca5d8697f16c4d979d8697f16c0d9735",
    "displayName" : "2015",
    "path" : "/news/2015"
  } ],
  "permissions" : {
    "create" : true,
    "read" : true,
    "update" : true,
    "delete" : true,
    "publish" : false,
    "readPublished" : false
  }
}