{
  "data" : [ {
    "uuid" : "d911bc585f93471791bc585f93b7176e",
    "creator" : {
      "firstName" : "Joe",
      "lastName" : "Doe",
      "uuid" : "9027ec4fa28d41c3a7ec4fa28d61c34c"
    },
    "created" : "2018-11-07T11:45:50.083366Z",
    "edited" : "2018-11-07T11:45:50.083385Z",
    "availableLanguages" : {
      "de" : {
        "published" : true,
        "version" : "1.0",
        "publisher" : {
          "firstName" : "Joe",
          "lastName" : "Doe",
          "uuid" : "70587f3497064d8c987f349706fd8ca2"
        },
        "publishDate" : "2018-11-07T11:45:50.083396Z"
      },
      "en" : {
        "published" : false,
        "version" : "1.1",
        "publisher" : {
          "firstName" : "Joe",
          "lastName" : "Doe",
          "uuid" : "104a3219900247fc8a3219900257fccc"
        },
        "publishDate" : "2018-11-07T11:45:50.083402Z"
      }
    },
    "languagePaths" : {
      "de" : "/api/v1/yourProject/webroot/Bilder",
      "en" : "/api/v1/yourProject/webroot/Images"
    },
    "parentNode" : {
      "uuid" : "23d038a2d6dd4dd09038a2d6ddadd08b",
      "displayName" : "parentNodeDisplayName"
    },
    "tags" : [ {
      "name" : "red",
      "uuid" : "681dcb8eacde4e5e9dcb8eacdeee5e10",
      "tagFamily" : "colors"
    }, {
      "name" : "red",
      "uuid" : "3fdd5930955040349d59309550c034e6",
      "tagFamily" : "colors"
    }, {
      "name" : "green",
      "uuid" : "5e344cf8afb34b39b44cf8afb36b39db",
      "tagFamily" : "colors"
    }, {
      "name" : "car",
      "uuid" : "db3476294c2f4da1b476294c2ffda1de"
    }, {
      "name" : "ship",
      "uuid" : "5e1f98409ff249109f98409ff2391084"
    } ],
    "childrenInfo" : {
      "folder" : {
        "schemaUuid" : "f47992b8c8584575b992b8c858a5757d",
        "count" : 5
      },
      "blogpost" : {
        "schemaUuid" : "0cfe8e60c4e44cb0be8e60c4e48cb0b8",
        "count" : 1
      }
    },
    "schema" : {
      "name" : "content",
      "uuid" : "75f9e72a4f054687b9e72a4f051687b2",
      "version" : "1.0"
    },
    "container" : false,
    "fields" : {
      "name" : "Name for language tag de-DE",
      "filename" : "dummy-content.de.html",
      "teaser" : "Dummy teaser for de-DE",
      "content" : "Content for language tag de-DE",
      "relatedProduct" : {
        "uuid" : "cd6ad8f9ef604007aad8f9ef60900713"
      },
      "price" : 100.1,
      "enabled" : true,
      "branch" : "2018-11-07T11:45:50.083418Z",
      "categories" : [ {
        "uuid" : "408210e242e443b18210e242e4c3b19e"
      }, {
        "uuid" : "d12cfaedd54a4ef8acfaedd54a3ef8c9"
      }, {
        "uuid" : "63d7ba98fb12460897ba98fb12460898"
      } ],
      "names" : [ "Jack", "Joe", "Mary", "Tom" ],
      "categoryIds" : [ 1, 42, 133, 7 ],
      "binary" : {
        "fileName" : "flower.jpg",
        "width" : 800,
        "height" : 600,
        "sha512sum" : "ec582eb760034dd91d5fd33656c0b56f082b7365d32e2a139dd9c87ebc192bff3525f32ff4c4137463a31cad020ac19e6e356508db2b90e32d737b6d725e14c1",
        "fileSize" : 95365,
        "mimeType" : "image/jpeg",
        "dominantColor" : "#22a7f0"
      },
      "location" : {
        "uuid" : "9035cc1f56654604b5cc1f56653604af",
        "microschema" : {
          "name" : "geolocation",
          "uuid" : "7d3d166b7984450ebd166b7984050ef4"
        },
        "fields" : {
          "latitude" : 48.208330230278,
          "longitude" : 16.373063840833
        }
      },
      "locations" : [ {
        "uuid" : "dc4bd90c07a0480f8bd90c07a0c80f09",
        "microschema" : {
          "name" : "geolocation",
          "uuid" : "e0e1ab1bdc9c4431a1ab1bdc9c243127"
        },
        "fields" : {
          "latitude" : 48.208330230278,
          "longitude" : 16.373063840833
        }
      }, {
        "uuid" : "0297f24b3eb5431897f24b3eb5331871",
        "microschema" : {
          "name" : "geolocation",
          "uuid" : "6d94dca7705f4b9d94dca7705fdb9dc6"
        },
        "fields" : {
          "latitude" : 48.137222,
          "longitude" : 11.575556
        }
      } ]
    },
    "path" : "/api/v1/yourProject/webroot/Images",
    "breadcrumb" : [ {
      "uuid" : "6766f08b2f664997a6f08b2f667997aa",
      "displayName" : "news",
      "path" : "/news"
    }, {
      "uuid" : "39a28f0b3fc346b6a28f0b3fc316b657",
      "displayName" : "2015",
      "path" : "/news/2015"
    } ],
    "permissions" : {
      "create" : true,
      "read" : true,
      "update" : true,
      "delete" : true,
      "publish" : false,
      "readPublished" : false
    }
  }, {
    "uuid" : "24388dc6fe534631b88dc6fe539631c8",
    "creator" : {
      "firstName" : "Joe",
      "lastName" : "Doe",
      "uuid" : "9f87fe8d53c1463b87fe8d53c1a63bf1"
    },
    "created" : "2018-11-07T11:45:50.083477Z",
    "editor" : {
      "firstName" : "Joe",
      "lastName" : "Doe",
      "uuid" : "2fe2a7c7a7364752a2a7c7a7368752f7"
    },
    "edited" : "2018-11-07T11:45:50.083482Z",
    "parentNode" : {
      "uuid" : "59a01d37b5594f3fa01d37b5592f3f59",
      "displayName" : "parentNodeDisplayName"
    },
    "tags" : [ {
      "name" : "red",
      "uuid" : "d0aff2845e7142b1aff2845e71a2b133",
      "tagFamily" : "colors"
    }, {
      "name" : "green",
      "uuid" : "048c2d6acdc74cba8c2d6acdc7acba84",
      "tagFamily" : "colors"
    }, {
      "name" : "car",
      "uuid" : "1e949cfbc24945ff949cfbc24935ff3a",
      "tagFamily" : "vehicles"
    }, {
      "name" : "ship",
      "uuid" : "e708d5b7fc3e41f588d5b7fc3ed1f5d2",
      "tagFamily" : "vehicles"
    } ],
    "childrenInfo" : { },
    "schema" : {
      "name" : "content",
      "uuid" : "19bc6f6724f14655bc6f6724f1865552",
      "version" : "1.0"
    },
    "container" : false,
    "fields" : {
      "name" : "Name for language tag en",
      "filename" : "dummy-content.en.html",
      "teaser" : "Dummy teaser for en",
      "content" : "Content for language tag en"
    },
    "breadcrumb" : [ {
      "uuid" : "95068a6156b44dd3868a6156b4add31f",
      "displayName" : "news",
      "path" : "/news"
    }, {
      "uuid" : "24b0554efb184098b0554efb18c098e0",
      "displayName" : "2015",
      "path" : "/news/2015"
    } ],
    "permissions" : {
      "create" : true,
      "read" : true,
      "update" : false,
      "delete" : false,
      "publish" : false,
      "readPublished" : false
    }
  } ],
  "_metainfo" : {
    "currentPage" : 1,
    "perPage" : 2,
    "pageCount" : 10,
    "totalCount" : 20
  }
}