{
  "uuid" : "8c2d555f82c54218ad555f82c5021856",
  "creator" : {
    "firstName" : "Joe",
    "lastName" : "Doe",
    "uuid" : "04c5f673b78a429f85f673b78ae29f22"
  },
  "created" : "2018-10-19T22:39:58.038Z",
  "editor" : {
    "firstName" : "Joe",
    "lastName" : "Doe",
    "uuid" : "2adcad1a1c9c417c9cad1a1c9c617cd3"
  },
  "edited" : "2018-10-19T22:39:58.038Z",
  "parentNode" : {
    "uuid" : "05f44182db0a479ab44182db0ac79af6",
    "displayName" : "parentNodeDisplayName"
  },
  "tags" : [ {
    "name" : "red",
    "uuid" : "162906d2da5e487aa906d2da5e987a6c",
    "tagFamily" : "colors"
  }, {
    "name" : "green",
    "uuid" : "d2f6506460644c3fb6506460640c3f19",
    "tagFamily" : "colors"
  }, {
    "name" : "car",
    "uuid" : "d267b52b0fcb49eca7b52b0fcb39ecd1",
    "tagFamily" : "vehicles"
  }, {
    "name" : "ship",
    "uuid" : "9f972152e0d74dcf972152e0d74dcfa9",
    "tagFamily" : "vehicles"
  } ],
  "childrenInfo" : { },
  "schema" : {
    "name" : "content",
    "uuid" : "8bb221a10cac40e4b221a10cac30e494",
    "version" : "1.0"
  },
  "container" : false,
  "fields" : {
    "name" : "Name for language tag en",
    "filename" : "dummy-content.en.html",
    "teaser" : "Dummy teaser for en",
    "content" : "Content for language tag en"
  },
  "breadcrumb" : [ {
    "uuid" : "1ce7968bac0c4a02a7968bac0cfa0240",
    "displayName" : "news",
    "path" : "/news"
  }, {
    "uuid" : "fb7620ecacc6497fb620ecacc6897f39",
    "displayName" : "2015",
    "path" : "/news/2015"
  } ],
  "permissions" : {
    "create" : true,
    "read" : true,
    "update" : false,
    "delete" : false,
    "publish" : false,
    "readPublished" : false
  }
}