{
  "data" : [ {
    "uuid" : "10b7612ed9d24340b7612ed9d253400d",
    "name" : "Hello World",
    "manifest" : {
      "name" : "Hello World",
      "apiName" : "hello-world",
      "description" : "A dummy plugin",
      "version" : "1.0",
      "author" : "Joe Doe",
      "inception" : "2018-11-20T12:12:04Z",
      "license" : "Apache License 2.0"
    }
  }, {
    "uuid" : "cef0ffdde7374ffbb0ffdde7376ffbd5",
    "name" : "Hello World",
    "manifest" : {
      "name" : "Hello World",
      "apiName" : "hello-world",
      "description" : "A dummy plugin",
      "version" : "1.0",
      "author" : "Joe Doe",
      "inception" : "2018-11-20T12:12:04Z",
      "license" : "Apache License 2.0"
    }
  }, {
    "uuid" : "55932e090970409a932e090970709a0e",
    "name" : "Hello World",
    "manifest" : {
      "name" : "Hello World",
      "apiName" : "hello-world",
      "description" : "A dummy plugin",
      "version" : "1.0",
      "author" : "Joe Doe",
      "inception" : "2018-11-20T12:12:04Z",
      "license" : "Apache License 2.0"
    }
  } ],
  "_metainfo" : {
    "currentPage" : 1,
    "perPage" : 25,
    "pageCount" : 1,
    "totalCount" : 3
  }
}