{
  "data" : [ {
    "uuid" : "9c22ab5016174f3ea2ab5016173f3e0a",
    "creator" : {
      "firstName" : "Joe",
      "lastName" : "Doe",
      "uuid" : "34780c1ab80b48b0b80c1ab80bb8b095"
    },
    "created" : "2018-10-19T22:39:57.920Z",
    "editor" : {
      "firstName" : "Joe",
      "lastName" : "Doe",
      "uuid" : "16b15e5e45b2499db15e5e45b2c99dfe"
    },
    "edited" : "2018-10-19T22:39:57.920Z",
    "name" : "Dummy project",
    "rootNode" : {
      "uuid" : "00a9e3fd8d754c9ca9e3fd8d759c9c8a"
    },
    "permissions" : {
      "create" : true,
      "read" : true,
      "update" : false,
      "delete" : true,
      "publish" : false,
      "readPublished" : false
    }
  }, {
    "uuid" : "1cdea39511b246789ea39511b2767872",
    "creator" : {
      "firstName" : "Joe",
      "lastName" : "Doe",
      "uuid" : "4cff54ac28724ea2bf54ac28723ea25f"
    },
    "created" : "2018-10-19T22:39:57.921Z",
    "editor" : {
      "firstName" : "Joe",
      "lastName" : "Doe",
      "uuid" : "9a2b104cf354498dab104cf354f98ddd"
    },
    "edited" : "2018-10-19T22:39:57.921Z",
    "name" : "Dummy Project (Mobile)",
    "rootNode" : {
      "uuid" : "9e43fbabf3864da783fbabf386dda7f0"
    },
    "permissions" : {
      "create" : true,
      "read" : true,
      "update" : false,
      "delete" : true,
      "publish" : false,
      "readPublished" : false
    }
  } ],
  "_metainfo" : {
    "currentPage" : 1,
    "perPage" : 2,
    "pageCount" : 10,
    "totalCount" : 20
  }
}