{
  "uuid" : "f2a61e4e1c714193a61e4e1c7171936a",
  "node" : {
    "uuid" : "f2a61e4e1c714193a61e4e1c7171936a",
    "creator" : {
      "firstName" : "Joe",
      "lastName" : "Doe",
      "uuid" : "55eb2db6372c4820ab2db6372cc82013"
    },
    "created" : "2018-10-01T14:21:19.724Z",
    "edited" : "2018-10-01T14:21:19.724Z",
    "availableLanguages" : {
      "de" : {
        "published" : true,
        "version" : "1.0",
        "publisher" : {
          "firstName" : "Joe",
          "lastName" : "Doe",
          "uuid" : "f843069971264d8083069971267d80ed"
        },
        "publishDate" : "2018-10-01T14:21:19.724Z"
      },
      "en" : {
        "published" : false,
        "version" : "1.1",
        "publisher" : {
          "firstName" : "Joe",
          "lastName" : "Doe",
          "uuid" : "3e8e43e922d547108e43e922d5a71025"
        },
        "publishDate" : "2018-10-01T14:21:19.724Z"
      }
    },
    "languagePaths" : {
      "de" : "/api/v1/yourProject/webroot/Bilder",
      "en" : "/api/v1/yourProject/webroot/Images"
    },
    "parentNode" : {
      "uuid" : "5bc4b726649e444f84b726649eb44ff2",
      "displayName" : "parentNodeDisplayName"
    },
    "tags" : [ {
      "name" : "red",
      "uuid" : "bc07c4ed0adb425a87c4ed0adb825a2c",
      "tagFamily" : "colors"
    }, {
      "name" : "red",
      "uuid" : "c2294a26f3af42e9a94a26f3af82e923",
      "tagFamily" : "colors"
    }, {
      "name" : "green",
      "uuid" : "9eddb471fdb94b8f9db471fdb9ab8f73",
      "tagFamily" : "colors"
    }, {
      "name" : "car",
      "uuid" : "1360ef1b160a45eda0ef1b160a25ede5"
    }, {
      "name" : "ship",
      "uuid" : "e1dade71c01f49e79ade71c01f49e7c1"
    } ],
    "childrenInfo" : {
      "folder" : {
        "schemaUuid" : "96ad5047289141b9ad5047289171b987",
        "count" : 5
      },
      "blogpost" : {
        "schemaUuid" : "e08c69762ac44b5f8c69762ac44b5fda",
        "count" : 1
      }
    },
    "schema" : {
      "name" : "content",
      "uuid" : "5d3e2581220f455bbe2581220fb55bd0",
      "version" : "1.0"
    },
    "container" : false,
    "fields" : {
      "name" : "Name for language tag de-DE",
      "filename" : "dummy-content.de.html",
      "teaser" : "Dummy teaser for de-DE",
      "content" : "Content for language tag de-DE",
      "relatedProduct" : {
        "uuid" : "49dd92fe01c74bc69d92fe01c76bc642"
      },
      "price" : 100.1,
      "enabled" : true,
      "branch" : "2018-10-01T14:21:19.724Z",
      "categories" : [ {
        "uuid" : "5069cbf5bf2648daa9cbf5bf26b8da62"
      }, {
        "uuid" : "999715c02a5248169715c02a52a81689"
      }, {
        "uuid" : "447fa8f34e6244e3bfa8f34e62a4e306"
      } ],
      "names" : [ "Jack", "Joe", "Mary", "Tom" ],
      "categoryIds" : [ 1, 42, 133, 7 ],
      "binary" : {
        "fileName" : "flower.jpg",
        "width" : 800,
        "height" : 600,
        "sha512sum" : "ec582eb760034dd91d5fd33656c0b56f082b7365d32e2a139dd9c87ebc192bff3525f32ff4c4137463a31cad020ac19e6e356508db2b90e32d737b6d725e14c1",
        "fileSize" : 95365,
        "mimeType" : "image/jpeg",
        "dominantColor" : "#22a7f0"
      },
      "location" : {
        "uuid" : "ff7009a11d2e4516b009a11d2e851608",
        "microschema" : {
          "name" : "geolocation",
          "uuid" : "fc364109acfe42c4b64109acfec2c4a4"
        },
        "fields" : {
          "latitude" : 48.208330230278,
          "longitude" : 16.373063840833
        }
      },
      "locations" : [ {
        "uuid" : "8ca4399b22ee4370a4399b22ee237096",
        "microschema" : {
          "name" : "geolocation",
          "uuid" : "8a5ae9f6770244749ae9f677025474ec"
        },
        "fields" : {
          "latitude" : 48.208330230278,
          "longitude" : 16.373063840833
        }
      }, {
        "uuid" : "6328243e7c4a4fb8a8243e7c4aefb87b",
        "microschema" : {
          "name" : "geolocation",
          "uuid" : "6948ae6202914dd588ae6202913dd5c4"
        },
        "fields" : {
          "latitude" : 48.137222,
          "longitude" : 11.575556
        }
      } ]
    },
    "path" : "/api/v1/yourProject/webroot/Images",
    "breadcrumb" : [ {
      "uuid" : "4de01563154149d2a01563154199d269",
      "displayName" : "news",
      "path" : "/news"
    }, {
      "uuid" : "f54cd3ebfb82433e8cd3ebfb82133ed9",
      "displayName" : "2015",
      "path" : "/news/2015"
    } ],
    "permissions" : {
      "create" : true,
      "read" : true,
      "update" : true,
      "delete" : true,
      "publish" : false,
      "readPublished" : false
    }
  },
  "children" : [ {
    "uuid" : "ee858db0367e4d63858db0367edd635d",
    "node" : {
      "uuid" : "ee858db0367e4d63858db0367edd635d",
      "creator" : {
        "firstName" : "Joe",
        "lastName" : "Doe",
        "uuid" : "1336457e8d7f4bfab6457e8d7fbbfa68"
      },
      "created" : "2018-10-01T14:21:19.724Z",
      "edited" : "2018-10-01T14:21:19.724Z",
      "availableLanguages" : {
        "de" : {
          "published" : true,
          "version" : "1.0",
          "publisher" : {
            "firstName" : "Joe",
            "lastName" : "Doe",
            "uuid" : "59c736f884774e1c8736f884772e1cf0"
          },
          "publishDate" : "2018-10-01T14:21:19.724Z"
        },
        "en" : {
          "published" : false,
          "version" : "1.1",
          "publisher" : {
            "firstName" : "Joe",
            "lastName" : "Doe",
            "uuid" : "1fa5b921d2644939a5b921d2640939df"
          },
          "publishDate" : "2018-10-01T14:21:19.724Z"
        }
      },
      "languagePaths" : {
        "de" : "/api/v1/yourProject/webroot/Bilder",
        "en" : "/api/v1/yourProject/webroot/Images"
      },
      "parentNode" : {
        "uuid" : "e253158911fb4bb193158911fb3bb156",
        "displayName" : "parentNodeDisplayName"
      },
      "tags" : [ {
        "name" : "red",
        "uuid" : "3b5ec502241144f69ec502241144f637",
        "tagFamily" : "colors"
      }, {
        "name" : "red",
        "uuid" : "c5c03b6cb11c418a803b6cb11c918a00",
        "tagFamily" : "colors"
      }, {
        "name" : "green",
        "uuid" : "4d272878ba0b4189a72878ba0b818996",
        "tagFamily" : "colors"
      }, {
        "name" : "car",
        "uuid" : "5fd2745dfab7497392745dfab73973b6"
      }, {
        "name" : "ship",
        "uuid" : "056c9546f40b4f9fac9546f40bdf9f6f"
      } ],
      "childrenInfo" : {
        "folder" : {
          "schemaUuid" : "f68e154f36a1479a8e154f36a1d79ad2",
          "count" : 5
        },
        "blogpost" : {
          "schemaUuid" : "02ee49c49d474ce0ae49c49d477ce039",
          "count" : 1
        }
      },
      "schema" : {
        "name" : "content",
        "uuid" : "7a8d636355e847d88d636355e807d821",
        "version" : "1.0"
      },
      "container" : false,
      "fields" : {
        "name" : "Name for language tag de-DE",
        "filename" : "dummy-content.de.html",
        "teaser" : "Dummy teaser for de-DE",
        "content" : "Content for language tag de-DE",
        "relatedProduct" : {
          "uuid" : "7c9b9cefe93246999b9cefe9327699c7"
        },
        "price" : 100.1,
        "enabled" : true,
        "branch" : "2018-10-01T14:21:19.724Z",
        "categories" : [ {
          "uuid" : "9e363227f4b7477db63227f4b7677d9d"
        }, {
          "uuid" : "ab80bb8e41cd4b5880bb8e41cdbb58a5"
        }, {
          "uuid" : "ad1395183c7d4c119395183c7d3c117f"
        } ],
        "names" : [ "Jack", "Joe", "Mary", "Tom" ],
        "categoryIds" : [ 1, 42, 133, 7 ],
        "binary" : {
          "fileName" : "flower.jpg",
          "width" : 800,
          "height" : 600,
          "sha512sum" : "ec582eb760034dd91d5fd33656c0b56f082b7365d32e2a139dd9c87ebc192bff3525f32ff4c4137463a31cad020ac19e6e356508db2b90e32d737b6d725e14c1",
          "fileSize" : 95365,
          "mimeType" : "image/jpeg",
          "dominantColor" : "#22a7f0"
        },
        "location" : {
          "uuid" : "5e6453f3e1c14351a453f3e1c1035135",
          "microschema" : {
            "name" : "geolocation",
            "uuid" : "99212d4499c94ac9a12d4499c9fac9d5"
          },
          "fields" : {
            "latitude" : 48.208330230278,
            "longitude" : 16.373063840833
          }
        },
        "locations" : [ {
          "uuid" : "83d48cbe8dba49dc948cbe8dbab9dc98",
          "microschema" : {
            "name" : "geolocation",
            "uuid" : "51bbbebd2d6f49e0bbbebd2d6f49e085"
          },
          "fields" : {
            "latitude" : 48.208330230278,
            "longitude" : 16.373063840833
          }
        }, {
          "uuid" : "c7c2e405de0046da82e405de0086da16",
          "microschema" : {
            "name" : "geolocation",
            "uuid" : "0d0da5256d6f47f98da5256d6fe7f96f"
          },
          "fields" : {
            "latitude" : 48.137222,
            "longitude" : 11.575556
          }
        } ]
      },
      "path" : "/api/v1/yourProject/webroot/Images",
      "breadcrumb" : [ {
        "uuid" : "26a3ba4624284134a3ba462428113452",
        "displayName" : "news",
        "path" : "/news"
      }, {
        "uuid" : "8b2ce0da9e10490bace0da9e10490b3f",
        "displayName" : "2015",
        "path" : "/news/2015"
      } ],
      "permissions" : {
        "create" : true,
        "read" : true,
        "update" : true,
        "delete" : true,
        "publish" : false,
        "readPublished" : false
      }
    }
  } ]
}