{
  "uuid" : "ba53a13fca2345cc93a13fca2325cc07",
  "creator" : {
    "firstName" : "Joe",
    "lastName" : "Doe",
    "uuid" : "590d250bc71e49848d250bc71ef9849b"
  },
  "created" : "2018-11-07T11:45:50.051355Z",
  "editor" : {
    "firstName" : "Joe",
    "lastName" : "Doe",
    "uuid" : "827a1ce02bed49eaba1ce02bed89ea80"
  },
  "edited" : "2018-11-07T11:45:50.051364Z",
  "name" : "Summer Collection Branch",
  "hostname" : "getmesh.io",
  "ssl" : true,
  "pathPrefix" : "my/prefix",
  "migrated" : true,
  "latest" : false,
  "tags" : [ {
    "name" : "dev",
    "uuid" : "462221f9b2d14994a221f9b2d1f9940f",
    "tagFamily" : "branchTags"
  }, {
    "name" : "prod",
    "uuid" : "d488f06633ec4a0d88f06633ecaa0d33",
    "tagFamily" : "branchTags"
  } ],
  "permissions" : {
    "create" : true,
    "read" : true,
    "update" : true,
    "delete" : true,
    "publish" : false,
    "readPublished" : false
  },
  "rolePerms" : {
    "create" : true,
    "read" : true,
    "update" : true,
    "delete" : true,
    "publish" : false,
    "readPublished" : false
  }
}